treeClass/treeClass.py
treeClass-1.0.1.dist-info/METADATA
treeClass-1.0.1.dist-info/WHEEL
treeClass-1.0.1.dist-info/top_level.txt
treeClass-1.0.1.dist-info/RECORD
